pyrebaselite/__init__.py
pyrebaselite/pyre_sseclient.py
pyrebaselite/pyrebaselite.py
pyrebase4lite-0.1.1.dist-info/WHEEL
pyrebase4lite-0.1.1.dist-info/METADATA
pyrebase4lite-0.1.1.dist-info/RECORD
