Metadata-Version: 2.1
Name: pyrebase4lite
Version: 0.1.1
Summary: 
Author: kengoon
Author-email: kengoon19@gmail.com
Requires-Python: >=3.7,<4.0
Classifier: Programming Language :: Python :: 3
Classifier: Programming Language :: Python :: 3.7
Classifier: Programming Language :: Python :: 3.8
Classifier: Programming Language :: Python :: 3.9
Classifier: Programming Language :: Python :: 3.10
Classifier: Programming Language :: Python :: 3.11
Requires-Dist: requests (>=2.28.2,<3.0.0)
Requires-Dist: requests-toolbelt (>=0.10.1,<0.11.0)
Requires-Dist: six (>=1.16.0,<2.0.0)
